solutionspace/__init__.py
solutionspace/engines/__init__.py
solutionspace/engines/backtracking.py
solutionspace/engines/bfs.py
solutionspace/engines/binary_search.py
solutionspace/engines/bitwise.py
solutionspace/engines/cyclic_sort.py
solutionspace/engines/dijkstra.py
solutionspace/engines/fast_slow.py
solutionspace/engines/intervals.py
solutionspace/engines/knapsack.py
solutionspace/engines/linked_list_reversal.py
solutionspace/engines/matrix.py
solutionspace/engines/monotonic_stack.py
solutionspace/engines/sampling.py
solutionspace/engines/sliding_window.py
solutionspace/engines/top_k.py
solutionspace/engines/topological_sort.py
solutionspace/engines/trie.py
solutionspace/engines/two_pointers.py
solutionspace/engines/union_find.py
solutionspace-0.1.0.dist-info/licenses/LICENSE
solutionspace-0.1.0.dist-info/METADATA
solutionspace-0.1.0.dist-info/WHEEL
solutionspace-0.1.0.dist-info/top_level.txt
solutionspace-0.1.0.dist-info/RECORD
