Metadata-Version: 2.4
Name: solutionspace
Version: 0.1.0
Summary: A generalized engine for solving algorithmic problems (LeetCode patterns).
Author: Future Intelligent Talent
Requires-Python: >=3.7
License-File: LICENSE
Dynamic: author
Dynamic: license-file
Dynamic: requires-python
Dynamic: summary
